
{
  "name": "DeltaExe",
  "identifier": "com.deltaexe.source",
  "apps": [
    {
      "beta": false,
      "name": "Deltaexe",
      "bundleIdentifier": "com.deltaexe.Delta",
      "developerName": "delta",
      "subtitle": "Delta executor.",
      "version": "v1.0",
      "versionDate": "2025-05-07T11:36:00+02:00",
      "versionDescription": "First",
      "downloadURL": "https://github.com/WhichChapter/probable-disco/releases/download/A/Delta-2.702.633.ipa",
      "localizedDescription": "DeltaExe is a delta executor.",
      "iconURL": "https://github.com/flyinghead/flycast/raw/master/shell/linux/flycast.png",
      "tintColor": "9b54fd",
      "size": 8161611,
      "screenshotURLs": [
        "https://github.com/flyinghead/flycast/raw/master/shell/imgs/screenshot1.png",
        "https://github.com/flyinghead/flycast/raw/master/shell/imgs/screenshot2.png",
        "https://github.com/flyinghead/flycast/raw/master/shell/imgs/screenshot3.png"
      ]
    }
  ]
}
